agentum/__init__.py
agentum-0.0.1.dist-info/METADATA
agentum-0.0.1.dist-info/WHEEL
agentum-0.0.1.dist-info/top_level.txt
agentum-0.0.1.dist-info/RECORD
