Metadata-Version: 2.4
Name: agentum
Version: 0.0.1
Summary: Cutting-edge AI agent framework
Requires-Python: >=3.10
